data_transformation_wizzard/__init__.py
data_transformation_wizzard/cross_correlation.py
data_transformation_wizzard/time_series_windowing.py
data_transformation_wizzard/transpose.py
data_transformation_wizzard-0.1.5.dist-info/METADATA
data_transformation_wizzard-0.1.5.dist-info/WHEEL
data_transformation_wizzard-0.1.5.dist-info/RECORD
