Metadata-Version: 2.1
Name: data_transformation_wizzard
Version: 0.1.5
Summary: Transpose.Windowing.Convolution
License: Edgaras Gacionis
Author: Edgaras Gacionis
Requires-Python: >=3.11,<4.0
Classifier: License :: Other/Proprietary License
Classifier: Programming Language :: Python :: 3
Classifier: Programming Language :: Python :: 3.11
Classifier: Programming Language :: Python :: 3.12
Requires-Dist: numpy (>=1.26,<2.0)
